poreana/__init__.py
poreana/adsorption.py
poreana/angle.py
poreana/density.py
poreana/diffusion.py
poreana/freeenergy.py
poreana/geometry.py
poreana/gyration.py
poreana/mc.py
poreana/model.py
poreana/sample.py
poreana/tables.py
poreana/utils.py
tests/__init__.py
tests/test_simple.py
poreana-0.2.3.dist-info/LICENSE
poreana-0.2.3.dist-info/METADATA
poreana-0.2.3.dist-info/WHEEL
poreana-0.2.3.dist-info/top_level.txt
poreana-0.2.3.dist-info/RECORD
