Metadata-Version: 2.1
Name: poreana
Version: 0.2.3
Summary: Pore system analysis tool.
Home-page: https://github.com/Ajax23/PoreAna
Author: Hamzeh Kraus
Author-email: kraus@itt.uni-stuttgart.de
Classifier: Programming Language :: Python :: 3
Classifier: License :: OSI Approved :: GNU General Public License v3 (GPLv3)
Classifier: Operating System :: OS Independent
Requires-Python: >=3.5
License-File: LICENSE
Requires-Dist: pandas
Requires-Dist: seaborn
Requires-Dist: scipy
Requires-Dist: chemfiles ==0.10.0
Requires-Dist: porems >=0.2.5
Requires-Dist: jinja2
Requires-Dist: h5py >=3.0.0
Requires-Dist: pyyaml
